muscle_mem/__init__.py
muscle_mem/check.py
muscle_mem/engine.py
muscle_mem/metrics.py
muscle_mem/dispatch/__init__.py
muscle_mem/dispatch/context.py
muscle_mem/dispatch/tool.py
muscle_mem/dispatch/tool_registry.py
muscle_mem/storage/__init__.py
muscle_mem/storage/db.py
muscle_mem/storage/types/__init__.py
muscle_mem/storage/types/arg.py
muscle_mem/storage/types/step.py
muscle_mem/storage/types/trajectory.py
muscle_mem/utils/__init__.py
muscle_mem/utils/metrics.py
muscle_mem-0.1.0.dist-info/METADATA
muscle_mem-0.1.0.dist-info/WHEEL
muscle_mem-0.1.0.dist-info/licenses/LICENSE
muscle_mem-0.1.0.dist-info/RECORD
