Metadata-Version: 2.4
Name: muscle-mem
Version: 0.1.0
Summary: muscle memory
Author-email: Erik Dunteman <erikdunteman@gmail.com>
License-File: LICENSE
Requires-Python: >=3.7
Requires-Dist: colorama
Provides-Extra: dev
Requires-Dist: build; extra == 'dev'
Requires-Dist: openai; extra == 'dev'
Requires-Dist: ruff>=0.3.0; extra == 'dev'
Requires-Dist: torch; extra == 'dev'
Requires-Dist: transformers; extra == 'dev'
Requires-Dist: twine; extra == 'dev'
